.hgignore
CHANGES.txt
LICENSE.txt
MANIFEST.in
README.txt
bootstrap.py
buildout.cfg
setup.py
js/__init__.py
js.rivets.egg-info/PKG-INFO
js.rivets.egg-info/SOURCES.txt
js.rivets.egg-info/dependency_links.txt
js.rivets.egg-info/entry_points.txt
js.rivets.egg-info/namespace_packages.txt
js.rivets.egg-info/not-zip-safe
js.rivets.egg-info/requires.txt
js.rivets.egg-info/top_level.txt
js/rivets/__init__.py
js/rivets/test_rivets.txt
js/rivets/resources/README.txt
js/rivets/resources/rivets.js
js/rivets/resources/rivets.min.js