Metadata-Version: 1.0
Name: js.rivets
Version: 0.4.4
Summary: Fanstatic packaging of Rivets
Home-page: https://bitbucket.org/gocept/js.rivets
Author: gocept Developers
Author-email: mail@gocept.com
License: BSD
Platform: UNKNOWN
